doepipeline
