Metadata-Version: 2.1
Name: doepipeline
Version: 1.1.1
Summary: Package for optimizing pipelines using DoE.
Home-page: https://github.com/clicumu/doepipeline
Author: Rickard Sjogren
Author-email: rickard.sjogren@umu.se
License: MIT
Keywords: pipeline doe optimization
Platform: UNKNOWN
Classifier: Development Status :: 4 - Beta
Classifier: License :: OSI Approved :: MIT License
Classifier: Programming Language :: Python :: 3.4
Classifier: Programming Language :: Python :: 3.5
Classifier: Programming Language :: Python :: 3.6
Classifier: Programming Language :: Python :: 3.7
Classifier: Topic :: Scientific/Engineering
Classifier: Operating System :: OS Independent
